{"errors":[],"warnings":[],"namedChunkGroups":{"polyfill":{"chunks":[2,0,8],"assets":["webpack-runtime-92101967f2432a6267d6.js","webpack-runtime-92101967f2432a6267d6.js.map","commons-4f907b2d61823eec4713.js","commons-4f907b2d61823eec4713.js.map","polyfill-96c0e71935cde5505b8a.js","polyfill-96c0e71935cde5505b8a.js.map"],"children":{},"childAssets":{}},"app":{"chunks":[2,1,7,4],"assets":["webpack-runtime-92101967f2432a6267d6.js","webpack-runtime-92101967f2432a6267d6.js.map","styles.edefbf8f82a35f46cde8.css","styles-e9d24b1846c7d6eb9685.js","styles-e9d24b1846c7d6eb9685.js.map","framework-83e11af5cf111be5ad89.js","framework-83e11af5cf111be5ad89.js.map","app-518f2c2d8cd7656bb4ad.js","app-518f2c2d8cd7656bb4ad.js.map"],"children":{},"childAssets":{}},"component---src-pages-404-js":{"chunks":[1,0,5],"assets":["styles.edefbf8f82a35f46cde8.css","styles-e9d24b1846c7d6eb9685.js","styles-e9d24b1846c7d6eb9685.js.map","commons-4f907b2d61823eec4713.js","commons-4f907b2d61823eec4713.js.map","component---src-pages-404-js-e78acbe3988229f685b6.js","component---src-pages-404-js-e78acbe3988229f685b6.js.map"],"children":{},"childAssets":{}},"component---src-pages-index-jsx":{"chunks":[1,3,0,6],"assets":["styles.edefbf8f82a35f46cde8.css","styles-e9d24b1846c7d6eb9685.js","styles-e9d24b1846c7d6eb9685.js.map","7794b142-558060ac074c5f32da13.js","7794b142-558060ac074c5f32da13.js.map","commons-4f907b2d61823eec4713.js","commons-4f907b2d61823eec4713.js.map","component---src-pages-index-jsx-fefb11ca0d085dc25932.js","component---src-pages-index-jsx-fefb11ca0d085dc25932.js.map"],"children":{},"childAssets":{}}},"assetsByChunkName":{"polyfill":["webpack-runtime-92101967f2432a6267d6.js","commons-4f907b2d61823eec4713.js","polyfill-96c0e71935cde5505b8a.js"],"app":["webpack-runtime-92101967f2432a6267d6.js","styles.edefbf8f82a35f46cde8.css","styles-e9d24b1846c7d6eb9685.js","framework-83e11af5cf111be5ad89.js","app-518f2c2d8cd7656bb4ad.js"],"component---src-pages-404-js":["styles.edefbf8f82a35f46cde8.css","styles-e9d24b1846c7d6eb9685.js","commons-4f907b2d61823eec4713.js","component---src-pages-404-js-e78acbe3988229f685b6.js"],"component---src-pages-index-jsx":["styles.edefbf8f82a35f46cde8.css","styles-e9d24b1846c7d6eb9685.js","7794b142-558060ac074c5f32da13.js","commons-4f907b2d61823eec4713.js","component---src-pages-index-jsx-fefb11ca0d085dc25932.js"]}}